{"version":6,"graphicsPipelines":{"383d888f441822ed":{"flags":8390656,"basePipelineHandle":"0000000000000000","basePipelineIndex":-1,"layout":"c6d2fe52447ad8aa","renderPass":"0000000000000000","subpass":0,"dynamicState":{"flags":0,"dynamicState":[3,6,7,8,4,1000267003,1000267004,1000267000,1000267001,1000267006,1000267007,1000267008,1000267010,1000267011,1000267002,5,1000267009]},"rasterizationState":{"flags":0,"depthBiasConstantFactor":0.0,"depthBiasSlopeFactor":0.0,"depthBiasClamp":0.0,"depthBiasEnable":1,"depthClampEnable":1,"polygonMode":0,"rasterizerDiscardEnable":0,"frontFace":0,"lineWidth":1.0,"cullMode":0},"viewportState":{"flags":0,"viewportCount":0,"scissorCount":0},"stages":[{"flags":0,"name":"MainVs","module":"54a8906e1c0beb70","stage":1}],"pNext":[{"sType":1000044002,"depthAttachmentFormat":0,"stencilAttachmentFormat":0,"viewMask":0},{"sType":1000320002,"flags":2}]}}}